[
  {
    "id": 1,
    "options": [
      {"id": 1, "text": "ことがあります"},
      {"id": 2, "text": "ものがあります"},
      {"id": 3, "text": "わけです"},
      {"id": 4, "text": "ところです"}
    ],
    "answer": 2
  },
  {
    "id": 2,
    "options": [
      {"id": 1, "text": "危ないばかりです"},
      {"id": 2, "text": "危ないはずです"},
      {"id": 3, "text": "危ないほどです"},
      {"id": 4, "text": "危ないところです"}
    ],
    "answer": 3
  },
  {
    "id": 3,
    "options": [
      {"id": 1, "text": "過ごしやすくする"},
      {"id": 2, "text": "暑くしている"},
      {"id": 3, "text": "涼しくする"},
      {"id": 4, "text": "快適にする"}
    ],
    "answer": 2
  },
  {
    "id": 4,
    "options": [
      {"id": 1, "text": "a ぬれた / b かわいた"},
      {"id": 2, "text": "a かわいた / b ぬれた"},
      {"id": 3, "text": "a ぬれた / b ぬれた"},
      {"id": 4, "text": "a かわいた / b かわいた"}
    ],
    "answer": 1
  },
  {
    "id": 5,
    "options": [
      {"id": 1, "text": "はともかく"},
      {"id": 2, "text": "どころか"},
      {"id": 3, "text": "ばかりで"},
      {"id": 4, "text": "のみならず"}
    ],
    "answer": 4
  }
]